treedrawer/__init__.py
treedrawer/treedraw.py
treedrawer-1.0.0.dist-info/METADATA
treedrawer-1.0.0.dist-info/WHEEL
treedrawer-1.0.0.dist-info/top_level.txt
treedrawer-1.0.0.dist-info/RECORD
