Metadata-Version: 2.4
Name: treedrawer
Version: 1.0.0
Summary: A simple ASCII tree drawing library
Author: Mehdi Akaaboune
Requires-Python: >=3.8
Dynamic: author
Dynamic: requires-python
Dynamic: summary
